VegZ/__init__.py
VegZ/clustering.py
VegZ/core.py
VegZ/diversity.py
VegZ/environmental.py
VegZ/functional_traits.py
VegZ/interactive_viz.py
VegZ/machine_learning.py
VegZ/multivariate.py
VegZ/nestedness.py
VegZ/spatial.py
VegZ/specialized_methods.py
VegZ/statistics.py
VegZ/temporal.py
VegZ/visualization.py
VegZ/data_management/__init__.py
VegZ/data_management/coordinate_systems.py
VegZ/data_management/darwin_core.py
VegZ/data_management/parsers.py
VegZ/data_management/remote_sensing.py
VegZ/data_management/standardization.py
VegZ/data_management/taxonomic_resolver.py
VegZ/data_management/transformations.py
VegZ/data_quality/__init__.py
VegZ/data_quality/spatial_validation.py
VegZ/data_quality/temporal_validation.py
vegz-1.3.0.dist-info/METADATA
vegz-1.3.0.dist-info/WHEEL
vegz-1.3.0.dist-info/licenses/LICENSE
vegz-1.3.0.dist-info/RECORD
