Metadata-Version: 2.4
Name: VegZ
Version: 1.3.0
Summary: A comprehensive Python package for vegetation data analysis and environmental modeling
Project-URL: Homepage, https://github.com/mhatim99/VegZ
Project-URL: Documentation, https://mhatim99.github.io/VegZ/
Project-URL: Repository, https://github.com/mhatim99/VegZ.git
Project-URL: Bug Reports, https://github.com/mhatim99/VegZ/issues
Project-URL: Changelog, https://github.com/mhatim99/VegZ/blob/main/CHANGELOG.md
Author-email: "Mohamed Z. Hatim" <mhatim4040@gmail.com>
License: MIT
License-File: LICENSE
Keywords: TWINSPAN,biodiversity,clustering,data-quality,diversity,ecology,elbow-analysis,environmental,error-detection,machine learning,modelling,multivariate,ordination,species-validation,taxonomic-names,vegetation
Classifier: Development Status :: 5 - Production/Stable
Classifier: Intended Audience :: Science/Research
Classifier: License :: OSI Approved :: MIT License
Classifier: Operating System :: OS Independent
Classifier: Programming Language :: Python :: 3
Classifier: Programming Language :: Python :: 3.8
Classifier: Programming Language :: Python :: 3.9
Classifier: Programming Language :: Python :: 3.10
Classifier: Programming Language :: Python :: 3.11
Classifier: Programming Language :: Python :: 3.12
Classifier: Programming Language :: Python :: 3.13
Classifier: Topic :: Scientific/Engineering :: Bio-Informatics
Classifier: Topic :: Scientific/Engineering :: Information Analysis
Requires-Python: >=3.8
Requires-Dist: matplotlib>=3.4.0
Requires-Dist: numpy>=1.21.0
Requires-Dist: pandas>=1.3.0
Requires-Dist: requests>=2.25.0
Requires-Dist: scikit-learn>=1.0.0
Requires-Dist: scipy>=1.7.0
Requires-Dist: seaborn>=0.11.0
Provides-Extra: dev
Requires-Dist: black>=21.0.0; extra == 'dev'
Requires-Dist: flake8>=3.9.0; extra == 'dev'
Requires-Dist: pytest-cov>=2.12.0; extra == 'dev'
Requires-Dist: pytest>=6.2.0; extra == 'dev'
Requires-Dist: sphinx-rtd-theme>=0.5.0; extra == 'dev'
Requires-Dist: sphinx>=4.0.0; extra == 'dev'
Provides-Extra: fuzzy
Requires-Dist: fuzzywuzzy>=0.18.0; extra == 'fuzzy'
Requires-Dist: python-levenshtein>=0.12.0; extra == 'fuzzy'
Provides-Extra: interactive
Requires-Dist: bokeh>=2.4.0; extra == 'interactive'
Requires-Dist: ipywidgets>=7.6.0; extra == 'interactive'
Requires-Dist: plotly>=5.0.0; extra == 'interactive'
Provides-Extra: remote-sensing
Requires-Dist: earthengine-api>=0.1.300; extra == 'remote-sensing'
Requires-Dist: geemap>=0.13.0; extra == 'remote-sensing'
Requires-Dist: netcdf4>=1.5.0; extra == 'remote-sensing'
Requires-Dist: xarray>=0.20.0; extra == 'remote-sensing'
Provides-Extra: spatial
Requires-Dist: geopandas>=0.10.0; extra == 'spatial'
Requires-Dist: pyproj>=3.2.0; extra == 'spatial'
Requires-Dist: rasterio>=1.2.0; extra == 'spatial'
Requires-Dist: shapely>=1.8.0; extra == 'spatial'
